batchman/__init__.py
batchman/batch_interfaces.py
batchman/batchman.py
batchman/cli.py
batchman/py.typed
batchman/models/__init__.py
batchman/models/batch.py
batchman/models/dataclasses.py
batchman/models/enums.py
batchman/models/provider_config.py
batchman/models/request.py
batchman/models/result.py
batchman/providers/__init__.py
batchman/providers/anthropic.py
batchman/providers/base.py
batchman/providers/config_store.py
batchman/providers/exxa.py
batchman/providers/openai.py
batchman/providers/registry.py
batchman/utils/__init__.py
batchman/utils/common.py
batchman/utils/envs.py
batchman/utils/files.py
batchman/utils/logging.py
batchman/utils/ui.py
batchman-1.1.0.dist-info/licenses/LICENSE
batchman-1.1.0.dist-info/METADATA
batchman-1.1.0.dist-info/WHEEL
batchman-1.1.0.dist-info/entry_points.txt
batchman-1.1.0.dist-info/top_level.txt
batchman-1.1.0.dist-info/RECORD
