Metadata-Version: 2.4
Name: batchman
Version: 1.1.0
Summary: A flexible Python library for managing batches of requests to LLM inference providers.
Author-email: Etienne <etienne@withexxa.com>
Maintainer-email: Etienne <etienne@withexxa.com>, Corentin <corentin@withexxa.com>
License: MIT License
Project-URL: bugs, https://github.com/withexxa/batchman/issues
Project-URL: changelog, https://github.com/withexxa/batchman/blob/master/changelog.md
Project-URL: homepage, https://github.com/withexxa/batchman
Classifier: Programming Language :: Python :: 3
Classifier: Programming Language :: Python :: 3.9
Classifier: Programming Language :: Python :: 3.10
Classifier: Programming Language :: Python :: 3.11
Classifier: Programming Language :: Python :: 3.12
Classifier: Programming Language :: Python :: 3.13
Classifier: Operating System :: OS Independent
Requires-Python: >=3.9
License-File: LICENSE
Requires-Dist: click
Requires-Dist: requests
Requires-Dist: pydantic
Requires-Dist: PrettyTable
Requires-Dist: textual
Requires-Dist: openai
Requires-Dist: anthropic
Provides-Extra: dev
Requires-Dist: coverage; extra == "dev"
Requires-Dist: mypy; extra == "dev"
Requires-Dist: pytest; extra == "dev"
Requires-Dist: ruff; extra == "dev"
Requires-Dist: types-requests; extra == "dev"
Requires-Dist: tox; extra == "dev"
Requires-Dist: tox-uv; extra == "dev"
Requires-Dist: sphinx; extra == "dev"
Requires-Dist: sphinx-rtd-theme; extra == "dev"
Requires-Dist: sphinx-autodoc-typehints; extra == "dev"
Dynamic: license-file
